MANIFEST.in
README.txt
setup.cfg
setup.py
cs/__init__.py
cs.featured.egg-info/PKG-INFO
cs.featured.egg-info/SOURCES.txt
cs.featured.egg-info/dependency_links.txt
cs.featured.egg-info/entry_points.txt
cs.featured.egg-info/namespace_packages.txt
cs.featured.egg-info/not-zip-safe
cs.featured.egg-info/requires.txt
cs.featured.egg-info/top_level.txt
cs/featured/__init__.py
cs/featured/config.py
cs/featured/configure.zcml
cs/featured/interfaces.py
cs/featured/rebuild_i18n.sh
cs/featured/content/__init__.py
cs/featured/content/configure.zcml
cs/featured/content/featured.py
cs/featured/locales/cs.featured-manual.pot
cs/featured/locales/cs.featured.pot
cs/featured/locales/plone-manual.pot
cs/featured/locales/plone.pot
cs/featured/locales/es/LC_MESSAGES/cs.featured.po
cs/featured/locales/es/LC_MESSAGES/plone.po
cs/featured/locales/eu/LC_MESSAGES/cs.featured.po
cs/featured/locales/eu/LC_MESSAGES/plone.po
cs/featured/portlets/__init__.py
cs/featured/portlets/configure.zcml
cs/featured/portlets/featuredportlet.pt
cs/featured/portlets/featuredportlet.py
cs/featured/profiles/default/factorytool.xml
cs/featured/profiles/default/metadata.xml
cs/featured/profiles/default/portlets.xml
cs/featured/profiles/default/rolemap.xml
cs/featured/profiles/default/types.xml
cs/featured/profiles/default/types/featured.xml
cs/featured/tests/__init__.py
cs/featured/tests/base_featuredportlet.py
cs/featured/tests/doc_tests.py
cs/featured/tests/test_featuredportlet.py
docs/HISTORY.txt
docs/INSTALL.txt
docs/LICENSE.GPL
docs/LICENSE.txt