Metadata-Version: 1.1
Name: cs.featured
Version: 1.1.1
Summary: Content-type to reference external things: title+image+url
Home-page: http://github.com/codesyntax/cs.featured
Author: Mikel Larreategi
Author-email: mlarreategi@codesyntax.com
License: GPL
Platform: UNKNOWN
Classifier: Framework :: Plone
Classifier: Programming Language :: Python
